{"cameraMode":{"drawMode":0,"name":"Shaded","section":"Shading Mode"},"sceneLighting":true,"audioPlay":false,"sceneViewState":{"m_AlwaysRefresh":true,"showFog":true,"showSkybox":true,"showFlares":true,"showImageEffects":true,"showParticleSystems":true,"showVisualEffectGraphs":true,"m_FxEnabled":true},"in2DMode":false,"pivot":{"x":-36.9296875,"y":513.6088256835938,"z":-472.3023681640625},"rotation":{"x":0.0400291308760643,"y":-0.340048223733902,"z":0.013766382820904255,"w":0.94022536277771},"size":1101.45361328125,"orthographic":false}